pyjarsigner/__init__.py
pyjarsigner/change.py
pyjarsigner/crypto.py
pyjarsigner/dirutils.py
pyjarsigner/jarutil.py
pyjarsigner/manifest.py
pyjarsigner-0.2.7.dist-info/LICENSE
pyjarsigner-0.2.7.dist-info/METADATA
pyjarsigner-0.2.7.dist-info/WHEEL
pyjarsigner-0.2.7.dist-info/RECORD
