Metadata-Version: 2.3
Name: pyjarsigner
Version: 0.2.7
Summary: Pure Python3 implementation to sign JAR and APK files
License: LGPL-3.0-only
Keywords: appknox,pyjarsigner,jarsigner,android,apksigner
Author: Subho Halder
Author-email: sunny@appknox.com
Requires-Python: >=3.8,<4.0
Classifier: Intended Audience :: Developers
Classifier: License :: OSI Approved :: GNU Lesser General Public License v3 (LGPLv3)
Classifier: Programming Language :: Python :: 3
Classifier: Programming Language :: Python :: 3.8
Classifier: Programming Language :: Python :: 3.9
Classifier: Programming Language :: Python :: 3.10
Classifier: Programming Language :: Python :: 3.11
Classifier: Programming Language :: Python :: 3.12
Classifier: Programming Language :: Python :: 3.13
Classifier: Topic :: Software Development :: Build Tools
Classifier: Topic :: Software Development :: Libraries :: Python Modules
Requires-Dist: m2crypto (==0.45.1)
